{
    "301708385": {
        "product_id": 301708385,
        "modelNbr": "WDP370PAHB",
        "Category": "APPLIANCES",
        "ApplType": "DISHWASHERS",
        "Type1": "PORTABLE DISHWASHERS",
        "Type2": "PORTABLE DISHWASHERS",
        "Title": "Whirlpool 24 in. Black Front Control Heavy-Duty Portable Dishwasher with 1 Hour Wash Cycle and 12-Place Settings, 64 dBA",
        "Brand": "Whirlpool",
        "ImageUrl": "https://images.homedepot-static.com/productImages/722f00fe-93db-4634-905a-59ecac8a25df/svn/black-whirlpool-portable-dishwashers-wdp370pahb-64_1000.jpg",
        "ProductPageUrl": "https://www.homedepot.com/p/Whirlpool-24-in-Black-Front-Control-Heavy-Duty-Portable-Dishwasher-with-1-Hour-Wash-Cycle-and-12-Place-Settings-64-dBA-WDP370PAHB/301708385",
        "Description": "We designed dishwashers with features for flexibility like the 1-Hour Wash cycle that makes sure you have dishes when you need them, how you need them. For clean, dry dishes straight from the dishwasher, use the Heated Dry option. Color: Black.",
        "depth": "27.5",
        "height": "37",
        "width": "24.13",
        "ratingValue": "4.2565",
        "reviewCount": "612",
        "price": 764,
        "priceValidUntil": "07/14/2021"
    },
    "313970211": {
        "product_id": 313970211,
        "modelNbr": "RDW1809-B-WHITE",
        "Category": "APPLIANCES",
        "ApplType": "DISHWASHERS",
        "Type1": "FRONT CONTROL",
        "Type2": "OTHER",
        "Title": "RCA 18 in. White Electronic Portable 120-volt Dishwasher with 3-Cycles with 8 Place Settings Capacity",
        "Brand": "RCA",
        "ImageUrl": "https://images.homedepot-static.com/productImages/a6a20686-0040-4ca4-8710-ce0777d83320/svn/white-rca-portable-dishwashers-rdw1809-b-white-64_1000.jpg",
        "ProductPageUrl": "https://www.homedepot.com/p/RCA-18-in-White-Electronic-Portable-120-volt-Dishwasher-with-3-Cycles-with-8-Place-Settings-Capacity-RDW1809-B-WHITE/313970211",
        "Description": "Washing dishes has never been more convenient or as easy as it is with this portable dishwasher. It is only 18 in. wide so it will easily fit in an apartment, mobile home or the cabin. However, it is large enough to accommodate an 8 piece place settings. With 6 wash programs you can choose the desired program according the soil level of your dishes. The sturdy castors make moving your dishwasher effortless. It is even Energy Star rated for year round energy and money saving. Color: White.",
        "depth": "23.62",
        "height": "35.63",
        "width": "17.63 in",
        "ratingValue": "4.0",
        "reviewCount": "26",
        "price": 599.99,
        "priceValidUntil": "7/4/2021"
    },
    "311411336": {
        "product_id": 311411336,
        "modelNbr": "GPT225SGLWW",
        "Category": "APPLIANCES",
        "ApplType": "DISHWASHERS",
        "Type1": "PORTABLE DISHWASHERS",
        "Type2": "PORTABLE DISHWASHERS",
        "Title": "GE 24 in. White Portable Dishwasher 120-Volt with 12 Place Settings Capacity and 54 dBA",
        "Brand": "GE",
        "ImageUrl": "https://images.homedepot-static.com/productImages/0f627652-5f38-4d9b-bb0d-54aed6f90a3f/svn/white-ge-portable-dishwashers-gpt225sglww-64_1000.jpg",
        "ProductPageUrl": "https://www.homedepot.com/p/GE-24-in-White-Portable-Dishwasher-120-Volt-with-12-Place-Settings-Capacity-and-54-dBA-GPT225SGLWW/311411336",
        "Description": "GE appliances provide up-to-date technology and exceptional quality to simplify the way you live. With a timeless appearance, this family of appliances is ideal for your family. And, coming from one of the most trusted names in America, you know that this entire selection of appliances is as advanced as it is practical. Color: White.",
        "depth": "25.375",
        "height": "36",
        "width": "23.6",
        "ratingValue": "3.9376",
        "reviewCount": "1267",
        "price": 628,
        "priceValidUntil": "07/14/2021"
    },
    "310333359": {
        "product_id": 310333359,
        "modelNbr": "FDW05ASBWHA",
        "Category": "APPLIANCES",
        "ApplType": "DISHWASHERS",
        "Type1": "FRONT CONTROL",
        "Type2": "OTHER",
        "Title": "Farberware 24 in. White Digital Portable 120-volt Dishwasher with 5-Cycles with 2-Place Setting Capacity",
        "Brand": "Farberware",
        "ImageUrl": "https://images.homedepot-static.com/productImages/a39e3289-81da-4ce1-b8e2-5419903fd4fb/svn/white-farberware-portable-dishwashers-fdw05asbwha-64_1000.jpg",
        "ProductPageUrl": "https://www.homedepot.com/p/Farberware-24-in-White-Digital-Portable-120-volt-Dishwasher-with-5-Cycles-with-2-Place-Setting-Capacity-FDW05ASBWHA/310333359",
        "Description": "If you have water, electricity and 40 minutes you can clean your dishes - anywhere and anytime! Whether it's in your kitchen, camping, on your boat or RV, or at an event, now dirty dishes are a thing of the past. The Farberware Professional Complete Dishwasher can be placed on any countertop or sturdy table and gives you the choice of using its built-in water tank or a quick faucet hookup. It offers 5 different wash cycles and can also be used to steam-clean baby bottles or give your glassware a sparkling clean finish. Color: White.",
        "depth": "17.3",
        "height": "17.3",
        "width": "16.5 in",
        "ratingValue": "4.3478",
        "reviewCount": "69",
        "price": 344.99,
        "priceValidUntil": "7/4/2021"
    },
    "206181617": {
        "product_id": 206181617,
        "modelNbr": "RDW3208",
        "Category": "APPLIANCES",
        "ApplType": "DISHWASHERS",
        "Type1": "DISHWASHERS S/O",
        "Type2": "OTHER",
        "Title": "RCA 24 in. White Electronic CounterTop Control 600120-volt Dishwasher with 6-Cycles, 6 Place Settings Capacity",
        "Brand": "RCA",
        "ImageUrl": "https://images.homedepot-static.com/productImages/79e416d7-2edd-414a-932a-c0d542046645/svn/white-rca-portable-dishwashers-rdw3208-64_1000.jpg",
        "ProductPageUrl": "https://www.homedepot.com/p/RCA-24-in-White-Electronic-CounterTop-Control-600120-volt-Dishwasher-with-6-Cycles-6-Place-Settings-Capacity-RDW3208/206181617",
        "Description": "The RCA electronic countertop dishwasher offers you easy to use push button controls, two cleaning speeds and a residual drying system. Push button controls let you easily program, pause or reset the cleaning cycle. Two cleaning speeds, heavy and normal, allows you choose just the right amount of cleaning power, heavy for your tough soiled pots and pans and normal for your gently used dishes. Our residual drying system collects and reuses the residual heat from the warm water inside the dishwasher to hygienically dry your dishes. Color: White.",
        "depth": "20",
        "height": "19.8",
        "width": "21.85",
        "ratingValue": "4.178",
        "reviewCount": "118",
        "price": 229.99,
        "priceValidUntil": "07/14/2021"
    },
    "311959703": {
        "product_id": 311959703,
        "modelNbr": "DDW1805EWP",
        "Category": "APPLIANCES",
        "ApplType": "DISHWASHERS",
        "Type1": "FRONT CONTROL",
        "Type2": "OTHER",
        "Title": "Danby 18 in. White Electronic Portable 115120-volt Dishwasher with 4-Cycles with 8-Place Settings Capacity",
        "Brand": "Danby",
        "ImageUrl": "https://images.homedepot-static.com/productImages/51d8a516-eeda-4dea-9160-1c5e149af678/svn/white-danby-portable-dishwashers-ddw1805ewp-64_1000.jpg",
        "ProductPageUrl": "https://www.homedepot.com/p/Danby-18-in-White-Electronic-Portable-115120-volt-Dishwasher-with-4-Cycles-with-8-Place-Settings-Capacity-DDW1805EWP/311959703",
        "Description": "Washing dishes has never been as much fun as it is with this versatile dishwasher by Danby. This attractive machine comes with a silverware basket, an eight place settings capacity and four different wash cycles. Its just 18 in. wide (45.7 cm) meaning it can easily be installed in condos and apartments and the convenient built-in castors allow you to move it around with ease. Your electricity bills wont take a beating with this smart and eco-friendly unit as it boasts a valuable low-water consumption function and is also ENERGY STAR rated. The appliance features a durable stainless-steel spray arm and interior making it the ideal dishwasher for remote cottage locations. In addition, youll find an automatic detergent dispenser and rinse-agent dispenser and the entire unit can easily be programmed by the state-of-the-art electronic controls. This highly-efficient model also comes with a 12-month warranty on parts and labor with in-home service. Color: White.",
        "depth": "23.63",
        "height": "35.63",
        "width": "17.69 in",
        "ratingValue": "3.9773",
        "reviewCount": "88",
        "price": 647.4,
        "priceValidUntil": "7/4/2021"
    }
}