{
    "309631042": {
        "product_id": 309631042,
        "modelNbr": "WT7900HBA",
        "Category": "APPLIANCES",
        "ApplType": "LAUNDRY",
        "Type1": "HE TL WITHOUT HOSES",
        "Type2": "HE TOP LOAD",
        "Title": "LG Electronics 5.5 cu. ft. High-Efficiency Mega Capacity Black Steel Top Load Smart Washer with TurboWash3D, ENERGY STAR",
        "Brand": "LG Electronics",
        "ImageUrl": "https://images.homedepot-static.com/productImages/e9d99552-25b3-45c0-bb45-2c60ca25cffe/svn/black-steel-lg-electronics-smart-washers-wt7900hba-64_1000.jpg",
        "ProductPageUrl": "https://www.homedepot.com/p/LG-Electronics-5-5-cu-ft-High-Efficiency-Mega-Capacity-Black-Steel-Top-Load-Smart-Washer-with-TurboWash3D-ENERGY-STAR-WT7900HBA/309631042",
        "Description": "Wash more in less time with 5.5 cu. ft. of mega capacity and TurboWash3D Technology that cuts down on wash times. Save time and energy without sacrificing performance with the WT7900 Series that brings the best of both worlds to your laundry room. Color: Black Steel.",
        "depth": "28.38 in",
        "height": "55.75",
        "width": "27 in",
        "ratingValue": "4.2947",
        "reviewCount": "302",
        "price": 1214,
        "priceValidUntil": "07/14/2021"
    },
    "314754195": {
        "product_id": 314754195,
        "modelNbr": "WKGX201HWA",
        "Category": "APPLIANCES",
        "ApplType": "LAUNDRY",
        "Type1": "WASHTOWER GAS",
        "Type2": "OTHER",
        "Title": "LG Electronics 27 in. White WashTower Laundry Center with 4.5 cu. ft. Washer and 7.4 cu. ft. Gas Dryer",
        "Brand": "LG Electronics",
        "ImageUrl": "https://images.homedepot-static.com/productImages/69026f51-7f62-4667-b246-39b3b89cdfa7/svn/white-lg-electronics-electric-dryers-wkgx201hwa-64_1000.jpg",
        "ProductPageUrl": "https://www.homedepot.com/p/LG-Electronics-27-in-White-WashTower-Laundry-Center-with-4-5-cu-ft-Washer-and-7-4-cu-ft-Gas-Dryer-WKGX201HWA/314754195",
        "Description": "Full-size and fully featured, with the washer on the bottom and dryer on top, the sleek single unit LG WashTower takes up half the space, giving you room to add a sink, a folding table or whatever you like. But unlike conventional stacked pairs, LG's exclusive Center Control panel is perfectly positioned with both washer and dryer controls at just the right height. Built-in intelligence makes laundry less of a chore by taking out the guesswork, while top-of-the-line innovations put advanced cleaning power within reach. Color: White.",
        "depth": "55",
        "height": "16.06",
        "width": "16.06",
        "ratingValue": "4.63",
        "reviewCount": "754",
        "price": 1798,
        "priceValidUntil": "07/14/2021"
    }
}