{
    "202988065": {
        "product_id": 202988065,
        "modelNbr": "ECK100BP",
        "Category": "APPLIANCES",
        "ApplType": "COOKING",
        "Type1": "FREE STANDING ELECTRIC",
        "Type2": "OTHER",
        "Title": "Premier 24 in. 2.97 cu. ft. Electric Range in Black",
        "Brand": "PREMIER",
        "ImageUrl": "https://images.homedepot-static.com/productImages/a370ef82-5b0a-4cdf-9ef1-b50eaf5fec2d/svn/black-premier-single-oven-electric-ranges-eck100bp-64_1000.jpg",
        "ProductPageUrl": "https://www.homedepot.com/p/Premier-24-in-2-97-cu-ft-Electric-Range-in-Black-ECK100BP/202988065",
        "Description": "The Premier 24 in. Freestanding Electric Range brings you the features you need while accommodating a smaller kitchen space. All Premier ranges come with an Exclusive Lifetime Warranty on all Top Burner Elements - Your assurance that you are purchasing a top quality product. Equipped with a lift-up cook top and support rod, this range is a cinch to keep clean. Safety features like the Surface Indicator Light, will let you know at a glance if cooktop burners are on. Color: Black.",
        "depth": "43",
        "height": "15",
        "width": "19",
        "ratingValue": "3.28",
        "reviewCount": "25",
        "price": 771.75,
        "priceValidUntil": "7/4/2021"
    },
    "202988066": {
        "product_id": 202988066,
        "modelNbr": "ECK100OP",
        "Category": "APPLIANCES",
        "ApplType": "COOKING",
        "Type1": "FREE STANDING ELECTRIC",
        "Type2": "AMANA",
        "Title": "Premier 24 in. 2.97 cu. ft. Electric Range in White",
        "Brand": "PREMIER",
        "ImageUrl": "https://images.homedepot-static.com/productImages/d73f8d15-76c4-4437-a1d2-5f7863394265/svn/white-premier-single-oven-electric-ranges-eck100op-64_1000.jpg",
        "ProductPageUrl": "https://www.homedepot.com/p/Premier-24-in-2-97-cu-ft-Electric-Range-in-White-ECK100OP/202988066",
        "Description": "The Premier 24 in. Freestanding Electric Range brings you the features you need while accommodating a smaller kitchen space. All Premier ranges come with an Exclusive Lifetime Warranty on all Top Burner Elements - Your assurance that you are purchasing a top quality product. Equipped with a lift-up cook top and support rod, this range is a cinch to keep clean. Safety features like the Surface Indicator Light, will let you know at a glance if cooktop burners are on. Color: White.",
        "depth": "43",
        "height": "15",
        "width": "19",
        "ratingValue": "3.6667",
        "reviewCount": "3",
        "price": 663,
        "priceValidUntil": "7/4/2021"
    },
    "309052082": {
        "product_id": 309052082,
        "modelNbr": "FFEH2422UW",
        "Category": "APPLIANCES",
        "ApplType": "COOKING",
        "Type1": "SLIDE IN ELECTRIC",
        "Type2": "OTHER",
        "Title": "Frigidaire 24 in. 1.9 cu. ft. Freestanding Electric Range with Manual Clean in White",
        "Brand": "Frigidaire",
        "ImageUrl": "https://images.homedepot-static.com/productImages/9237637f-c093-4bb9-a577-831c49a372b9/svn/white-frigidaire-single-oven-electric-ranges-ffeh2422uw-64_1000.jpg",
        "ProductPageUrl": "https://www.homedepot.com/p/Frigidaire-24-in-1-9-cu-ft-Freestanding-Electric-Range-with-Manual-Clean-in-White-FFEH2422UW/309052082",
        "Description": "This 24 in. electric range is compact in design, but not in capacity - oven can easily fit a 10 lb. turkey. Convenient storage drawer offers extra space to store your cookware. Keeping the bottom of your oven clean is easier with a hidden heating element. The stylish knobs are color-coordinated to match the finish of the range. ADA Compliant. Color: White.",
        "depth": "41.5",
        "height": "12.875",
        "width": "16.38",
        "ratingValue": "4.0976",
        "reviewCount": "41",
        "price": 629,
        "priceValidUntil": "07/14/2021"
    },
    "202988060": {
        "product_id": 202988060,
        "modelNbr": "EAK220OP",
        "Category": "APPLIANCES",
        "ApplType": "COOKING",
        "Type1": "FREE STANDING ELECTRIC",
        "Type2": "OTHER",
        "Title": "Premier 20 in. 2.42 cu. ft. Electric Range in White",
        "Brand": "PREMIER",
        "ImageUrl": "https://images.homedepot-static.com/productImages/ec291d6a-99ec-41ef-8546-698166ff5192/svn/white-premier-single-oven-electric-ranges-eak220op-64_1000.jpg",
        "ProductPageUrl": "https://www.homedepot.com/p/Premier-20-in-2-42-cu-ft-Electric-Range-in-White-EAK220OP/202988060",
        "Description": "The Premier 20 in. Freestanding Electric Range puts all the features and convenience of a full-size range into a unit that will accommodate even the most intimate of kitchen spaces. All Premier ranges come with an Exclusive Lifetime Warranty on all Top Burner Elements - Your assurance that you are purchasing a top quality product. Equipped with a lift-up cook top and support rod, this range is a cinch to keep clean. Safety features like the Surface Indicator Light, will let you know at a glance if cooktop burners are on. Our \"Keep Warm\" Thermostat enables you to set your range to 150°, keeping your food warm without continuing to cook until ready to eat and the Fully Insulated Oven comes with 2 Heavy-Duty Oven Racks with 4 Adjustable Positions. Color: White.",
        "depth": "41",
        "height": "14.5",
        "width": "16",
        "ratingValue": "3.5385",
        "reviewCount": "13",
        "price": 752.85,
        "priceValidUntil": "7/4/2021"
    },
    "300052261": {
        "product_id": 300052261,
        "modelNbr": "ECS2X0BP",
        "Category": "APPLIANCES",
        "ApplType": "COOKING",
        "Type1": "FREE STANDING ELECTRIC",
        "Type2": "OTHER",
        "Title": "Premier 24 in. 2.97 cu. ft. Freestanding Smooth Top Electric Range in Black",
        "Brand": "PREMIER",
        "ImageUrl": "https://images.homedepot-static.com/productImages/bb43d67c-979c-4e31-87b7-055e16cc3c4c/svn/black-premier-single-oven-electric-ranges-ecs2x0bp-64_1000.jpg",
        "ProductPageUrl": "https://www.homedepot.com/p/Premier-24-in-2-97-cu-ft-Freestanding-Smooth-Top-Electric-Range-in-Black-ECS2X0BP/300052261",
        "Description": "The Premier 24 in. Freestanding Electric Range brings you the features you need while accommodating a smaller kitchen space. All Premier ranges come with an Exclusive Lifetime Warranty on all Top Burner Elements - Your assurance that you are purchasing a top quality product. Color: Black.",
        "depth": "43",
        "height": "15",
        "width": "19",
        "ratingValue": "3.7321",
        "reviewCount": "56",
        "price": 1017.53,
        "priceValidUntil": "7/4/2021"
    },
    "202988062": {
        "product_id": 202988062,
        "modelNbr": "EAK600BP",
        "Category": "APPLIANCES",
        "ApplType": "COOKING",
        "Type1": "FREE STANDING ELECTRIC",
        "Type2": "OTHER",
        "Title": "Premier 20 in. 2.42 cu. ft. Electric Range in Stainless Steel, Silver",
        "Brand": "PREMIER",
        "ImageUrl": "https://images.homedepot-static.com/productImages/6ac0fea0-beec-4b47-bf03-a718e4579c41/svn/stainless-steel-premier-single-oven-electric-ranges-eak600bp-64_1000.jpg",
        "ProductPageUrl": "https://www.homedepot.com/p/Premier-20-in-2-42-cu-ft-Electric-Range-in-Stainless-Steel-EAK600BP/202988062",
        "Description": "The Premier 20 in. Freestanding Electric Range puts all the features and convenience of a full-size range into a unit that will accommodate even the most intimate of kitchen spaces. All Premier ranges come with an Exclusive Lifetime Warranty on all Top Burner Elements - Your assurance that you are purchasing a top quality product. Equipped with a lift-up cook top and support rod, this range is a cinch to keep clean. Safety features like the Surface Indicator Light, will let you know at a glance if cooktop burners are on. Our \"Keep Warm\" Thermostat enables you to set your range to 150°, keeping your food warm without continuing to cook until ready to eat and the Fully Insulated Oven comes with 2 Heavy-Duty Oven Racks with 4 Adjustable Positions. Color: Stainless Steel.",
        "depth": "41",
        "height": "14.5",
        "width": "16",
        "ratingValue": "4.2",
        "reviewCount": "5",
        "price": 1009.65,
        "priceValidUntil": "7/4/2021"
    },
    "202988064": {
        "product_id": 202988064,
        "modelNbr": "EAKLOHOP",
        "Category": "APPLIANCES",
        "ApplType": "COOKING",
        "Type1": "FREE STANDING ELECTRIC",
        "Type2": "OTHER",
        "Title": "Premier 20 in. 2.42 cu. ft. Electric Range in White",
        "Brand": "PREMIER",
        "ImageUrl": "https://images.homedepot-static.com/productImages/ebe07c65-8373-4fde-8dac-4f569394b569/svn/white-premier-single-oven-electric-ranges-eaklohop-64_1000.jpg",
        "ProductPageUrl": "https://www.homedepot.com/p/Premier-20-in-2-42-cu-ft-Electric-Range-in-White-EAKLOHOP/202988064",
        "Description": "The Premier 20 in. Freestanding Electric Range puts all the features and convenience of a full-size range into a unit that will accommodate even the most intimate of kitchen spaces. All Premier ranges come with an Exclusive Lifetime Warranty on all Top Burner Elements - Your assurance that you are purchasing a top quality product. Equipped with a lift-up cook top and support rod, this range is a cinch to keep clean. Safety features like the Surface Indicator Light, will let you know at a glance if cooktop burners are on. Our \"Keep Warm\" Thermostat enables you to set your range to 150°, keeping your food warm without continuing to cook until ready to eat and the Fully Insulated Oven comes with 2 Heavy-Duty Oven Racks with 4 Adjustable Positions. Color: White.",
        "depth": "41",
        "height": "14.5",
        "width": "16",
        "ratingValue": "4.0",
        "reviewCount": "10",
        "price": 666.75,
        "priceValidUntil": "7/4/2021"
    },
    "306195372": {
        "product_id": 306195372,
        "modelNbr": "QAS740RMSS",
        "Category": "APPLIANCES",
        "ApplType": "COOKING",
        "Type1": "FREE STANDING ELECTRIC",
        "Type2": "OTHER",
        "Title": "Haier 24 in. 2.9 cu. ft. Electric Range with Self-Cleaning Convection Oven in Stainless Steel, Silver",
        "Brand": "Haier",
        "ImageUrl": "https://images.homedepot-static.com/productImages/47469de4-ebe2-49ad-abbf-9373170a3059/svn/stainless-steel-haier-single-oven-electric-ranges-qas740rmss-64_1000.jpg",
        "ProductPageUrl": "https://www.homedepot.com/p/Haier-24-in-2-9-cu-ft-Electric-Range-with-Self-Cleaning-Convection-Oven-in-Stainless-Steel-QAS740RMSS/306195372",
        "Description": "The Haier 2.9 cu. ft. Electric Range provides a convection cooking to meet all cooking needs. The ceramic smooth glass cooking surface provides a sleek appearance and is easy to clean. This versatile design gives you the option for a tradition look, or the ability to flip down to create a slide-in appearance. Color: Stainless Steel.",
        "depth": "45.625",
        "height": "15.375",
        "width": "19",
        "ratingValue": "4.3288",
        "reviewCount": "73",
        "price": 1258,
        "priceValidUntil": "07/14/2021"
    },
    "300052169": {
        "product_id": 300052169,
        "modelNbr": "ECS2X0OP",
        "Category": "APPLIANCES",
        "ApplType": "COOKING",
        "Type1": "FREE STANDING ELECTRIC",
        "Type2": "OTHER",
        "Title": "Premier 24 in. 2.97 cu. ft. Freestanding Smooth Top Electric Range in White",
        "Brand": "PREMIER",
        "ImageUrl": "https://images.homedepot-static.com/productImages/3e7b0dae-1975-4894-81c9-9298de78ee7a/svn/white-premier-single-oven-electric-ranges-ecs2x0op-64_1000.jpg",
        "ProductPageUrl": "https://www.homedepot.com/p/Premier-24-in-2-97-cu-ft-Freestanding-Smooth-Top-Electric-Range-in-White-ECS2X0OP/300052169",
        "Description": "The Premier 24 in. Freestanding Electric Range brings you the features you need while accommodating a smaller kitchen space. All Premier ranges come with an Exclusive Lifetime Warranty on all Top Burner Elements - Your assurance that you are purchasing a top quality product. Color: White.",
        "depth": "43",
        "height": "15",
        "width": "19",
        "ratingValue": "3.4286",
        "reviewCount": "14",
        "price": 1011.15,
        "priceValidUntil": "7/4/2021"
    },
    "204489380": {
        "product_id": 204489380,
        "modelNbr": "TEM110BRWY",
        "Category": "APPLIANCES",
        "ApplType": "COOKING",
        "Type1": "COOKING S/O",
        "Type2": "OTHER",
        "Title": "Summit Appliance 20 in. 2.5 cu. ft. Slide-In Electric Range in Stainless Steel, Silver",
        "Brand": "SUMMIT APPLIANCE",
        "ImageUrl": "https://images.homedepot-static.com/productImages/c4835397-a40f-4cf1-87ef-e0acf769d2c2/svn/stainless-steel-summit-appliance-single-oven-electric-ranges-tem110brwy-64_1000.jpg",
        "ProductPageUrl": "https://www.homedepot.com/p/Summit-Appliance-20-in-2-5-cu-ft-Slide-In-Electric-Range-in-Stainless-Steel-TEM110BRWY/204489380",
        "Description": "Summit Professional brings luxury to apartment sized ranges with our exclusive line of 'slide-in' look ovens. The TEM110BRWY electric range is conveniently sized at just 20 in. wide to fit into even the tightest of kitchen spaces. Elegant stainless steel doors on the oven and lower storage compartment are matched with solid towel bar style handles. Our 'slide-in' units have a low stainless top frame that lets you customize the wall behind your range without planning around a backguard. A stainless steel manifold completes the modern look. Solidly constructed from black porcelain and steel, the TEM110BRWY is easy to clean and striking to view. The oven has a clear window and light so you can keep a watch on your cooking. Enjoy the best meals in unique style with lasting durability.",
        "depth": "40",
        "height": "14",
        "width": "16",
        "ratingValue": "3.6667",
        "reviewCount": "12",
        "price": 968.75,
        "priceValidUntil": "7/4/2021"
    },
    "302692526": {
        "product_id": 302692526,
        "modelNbr": "MCSRE24S",
        "Category": "APPLIANCES",
        "ApplType": "COOKING",
        "Type1": "FREE STANDING ELECTRIC",
        "Type2": "OTHER",
        "Title": "Magic Chef 24 in. 2.2 cu. ft. Electric Range with Convection in Stainless Steel, Silver",
        "Brand": "Magic Chef",
        "ImageUrl": "https://images.homedepot-static.com/productImages/3844e156-b79c-467a-a970-fd3ef4731e27/svn/stainless-steel-magic-chef-single-oven-electric-ranges-mcsre24s-64_1000.jpg",
        "ProductPageUrl": "https://www.homedepot.com/p/Magic-Chef-24-in-2-2-cu-ft-Electric-Range-with-Convection-in-Stainless-Steel-MCSRE24S/302692526",
        "Description": "The Magic Chef 24 in. wide freestanding electric range is perfect for smaller spaces, yet lets you prepare family size meals. The programmable convection oven features seven cooking modes. Its 4-radiant element ceramic cooktop with a smooth surface allows for quick and easy cleaning. Its sleek stainless steel exterior complements any decor. Just like a full size range, there is a digital clock and timer, 2 oven racks, as well as anti-tilt bracket and adjustable legs.",
        "depth": "41",
        "height": "17.9",
        "width": "13.1",
        "ratingValue": "3.8537",
        "reviewCount": "41",
        "price": 899,
        "priceValidUntil": "7/4/2021"
    },
    "309297432": {
        "product_id": 309297432,
        "modelNbr": "PRE2015GW",
        "Category": "APPLIANCES",
        "ApplType": "COOKING",
        "Type1": "FREE STANDING ELECTRIC",
        "Type2": "OTHER",
        "Title": "PREMIUM 20 in. 2.2 cu. ft. Electric Range in White",
        "Brand": "PREMIUM",
        "ImageUrl": "https://images.homedepot-static.com/productImages/818c0b13-8c27-4d90-9ec4-61b40c424c7f/svn/white-premium-single-oven-electric-ranges-pre2015gw-64_1000.jpg",
        "ProductPageUrl": "https://www.homedepot.com/p/PREMIUM-20-in-2-2-cu-ft-Electric-Range-in-White-PRE2015GW/309297432",
        "Description": "PREMIUM's 20 in. 2.2 cu. ft. Electric Range in White is the perfect appliance for your apartment, condo or office kitchen. Just as in larger units there is an in-door window and oven light to allow users to check on food while it is cooking, 2 adjustable wire racks, a broiler tray and grid included, and a handy removable storage drawer. With its small footprint, it conserves space while providing all the functionality you need to cook healthy meals at home.",
        "depth": "33.86",
        "height": "17.13",
        "width": "13.78",
        "ratingValue": "3.5",
        "reviewCount": "2",
        "price": 533.49,
        "priceValidUntil": "7/4/2021"
    },
    "202988073": {
        "product_id": 202988073,
        "modelNbr": "ECK3X0BP",
        "Category": "APPLIANCES",
        "ApplType": "COOKING",
        "Type1": "FREE STANDING ELECTRIC",
        "Type2": "OTHER",
        "Title": "Premier 24 in. 2.97 cu. ft. Electric Range in Black",
        "Brand": "PREMIER",
        "ImageUrl": "https://images.homedepot-static.com/productImages/7303c7d6-03dd-4f12-87db-3e9423ac3054/svn/black-premier-single-oven-electric-ranges-eck3x0bp-64_1000.jpg",
        "ProductPageUrl": "https://www.homedepot.com/p/Premier-24-in-2-97-cu-ft-Electric-Range-in-Black-ECK3X0BP/202988073",
        "Description": "The Premier 24 in. Freestanding Electric Range brings you the features you need while accommodating a smaller kitchen space. All Premier ranges come with an Exclusive Lifetime Warranty on all Top Burner Elements - Your assurance that you are purchasing a top quality product. Equipped with a lift-up cook top and support rod, this range is a cinch to keep clean. Safety features like the Surface Indicator Light, will let you know at a glance if cooktop burners are on. Color: Black.",
        "depth": "43",
        "height": "15",
        "width": "19",
        "ratingValue": "4.0",
        "reviewCount": "2",
        "price": 866.25,
        "priceValidUntil": "7/4/2021"
    },
    "306294962": {
        "product_id": 306294962,
        "modelNbr": "RAS240DMWW",
        "Category": "APPLIANCES",
        "ApplType": "COOKING",
        "Type1": "FREE STANDING ELECTRIC",
        "Type2": "OTHER",
        "Title": "Hotpoint 24 in. 2.9 cu. ft. Electric Range Oven in White",
        "Brand": "Hotpoint",
        "ImageUrl": "https://images.homedepot-static.com/productImages/e2900748-2e07-4af0-9f85-128a43e1f141/svn/white-hotpoint-single-oven-electric-ranges-ras240dmww-64_1000.jpg",
        "ProductPageUrl": "https://www.homedepot.com/p/Hotpoint-24-in-2-9-cu-ft-Electric-Range-Oven-in-White-RAS240DMWW/306294962",
        "Description": "GE appliances provide up-to-date technology and exceptional quality to simplify the way you live. With a timeless appearance, this family of appliances is ideal for your family. And, coming from one of the most trusted names in America, you know that this entire selection of appliances is as advanced as it is practical. Color: White.",
        "depth": "44.375",
        "height": "15.375",
        "width": "19",
        "ratingValue": "4.0333",
        "reviewCount": "60",
        "price": 584,
        "priceValidUntil": "07/14/2021"
    },
    "311571252": {
        "product_id": 311571252,
        "modelNbr": "ERU240P0W",
        "Category": "APPLIANCES",
        "ApplType": "COOKING",
        "Type1": "FREE STANDING ELECTRIC",
        "Type2": "OTHER",
        "Title": "Avanti 24 in. 2.6 cu. ft. Single Oven Electric Range in White",
        "Brand": "Avanti",
        "ImageUrl": "https://images.homedepot-static.com/productImages/96f76687-4519-42e8-9c4f-a54d89c3c908/svn/white-avanti-single-oven-electric-ranges-eru240p0w-64_1000.jpg",
        "ProductPageUrl": "https://www.homedepot.com/p/Avanti-24-in-2-6-cu-ft-Single-Oven-Electric-Range-in-White-ERU240P0W/311571252",
        "Description": "This 24 in. freestanding electric range is ideally designed to fit in any kitchen interior. The oven is equipped with a light that illuminates the oven to enable visual control of the food by turning the switch on or off, whereas precise temperature can be reached by rotating the thermostat clockwise. The power indicator light signals when the heat elements are switched On/Off. Color: White.",
        "depth": "18",
        "height": "25",
        "width": "20",
        "ratingValue": "4.0",
        "reviewCount": "3",
        "price": 585,
        "priceValidUntil": "7/4/2021"
    },
    "306294968": {
        "product_id": 306294968,
        "modelNbr": "RAS300DMWW",
        "Category": "APPLIANCES",
        "ApplType": "COOKING",
        "Type1": "FREE STANDING ELECTRIC",
        "Type2": "FRIGIDAIRE",
        "Title": "Hotpoint 24 in. 2.9 cu. ft. Electric Range Oven in White",
        "Brand": "Hotpoint",
        "ImageUrl": "https://images.homedepot-static.com/productImages/24cf5f6d-f9b1-49d7-92cb-6998e2a5a9b5/svn/white-hotpoint-single-oven-electric-ranges-ras300dmww-64_1000.jpg",
        "ProductPageUrl": "https://www.homedepot.com/p/Hotpoint-24-in-2-9-cu-ft-Electric-Range-Oven-in-White-RAS300DMWW/306294968",
        "Description": "GE appliances provide up-to-date technology and exceptional quality to simplify the way you live. With a timeless appearance, this family of appliances is ideal for your family. And, coming from one of the most trusted names in America, you know that this entire selection of appliances is as advanced as it is practical. Color: White.",
        "depth": "44.375",
        "height": "15.375",
        "width": "19",
        "ratingValue": "4.0886",
        "reviewCount": "79",
        "price": 628,
        "priceValidUntil": "07/14/2021"
    },
    "306283705": {
        "product_id": 306283705,
        "modelNbr": "JAS640RMSS",
        "Category": "APPLIANCES",
        "ApplType": "COOKING",
        "Type1": "FREE STANDING ELECTRIC",
        "Type2": "GE",
        "Title": "24 in. 2.9 cu. ft. Electric Range with Steam-Cleaning Oven in Stainless Steel, Silver",
        "Brand": "GE",
        "ImageUrl": "https://images.homedepot-static.com/productImages/8bae316e-7d2a-4fd5-a4fa-b04ac261c749/svn/stainless-steel-ge-single-oven-electric-ranges-jas640rmss-64_1000.jpg",
        "ProductPageUrl": "https://www.homedepot.com/p/GE-24-in-2-9-cu-ft-Electric-Range-with-Steam-Cleaning-Oven-in-Stainless-Steel-JAS640RMSS/306283705",
        "Description": "GE appliances provide up-to-date technology and exceptional quality to simplify the way you live. With a timeless appearance, this family of appliances is ideal for your family. And, coming from one of the most trusted names in America, you know that this entire selection of appliances is as advanced as it is practical. Color: Stainless Steel.",
        "depth": "45.625",
        "height": "15.375",
        "width": "19",
        "ratingValue": "4.1445",
        "reviewCount": "173",
        "price": 944,
        "priceValidUntil": "07/14/2021"
    },
    "301398972": {
        "product_id": 301398972,
        "modelNbr": "ER20P3SG",
        "Category": "APPLIANCES",
        "ApplType": "COOKING",
        "Type1": "FREE STANDING ELECTRIC",
        "Type2": "OTHER",
        "Title": "Avanti 20 in. 2.1 cu. ft. Electric Range in Stainless Steel, Silver",
        "Brand": "Avanti",
        "ImageUrl": "https://images.homedepot-static.com/productImages/2856ed25-3a42-49b1-b9a5-a1785d1abeeb/svn/stainless-steel-avanti-single-oven-electric-ranges-er20p3sg-64_1000.jpg",
        "ProductPageUrl": "https://www.homedepot.com/p/Avanti-20-in-2-1-cu-ft-Electric-Range-in-Stainless-Steel-ER20P3SG/301398972",
        "Description": "This Avanti 20 in. Electric Range Comes with a Backsplash and Storage Drawer. It features 4 coil burners, 2.1 cu. ft. capacity, deluxe see-thru glass oven door, oven cavity light, a backsplash and leveling legs. Color: Stainless Steel.",
        "depth": "34.5",
        "height": "35.75",
        "width": "18.5",
        "ratingValue": "3.2727",
        "reviewCount": "11",
        "price": 692.47,
        "priceValidUntil": "7/4/2021"
    },
    "301398974": {
        "product_id": 301398974,
        "modelNbr": "ER20P0WG",
        "Category": "APPLIANCES",
        "ApplType": "COOKING",
        "Type1": "FREE STANDING ELECTRIC",
        "Type2": "OTHER",
        "Title": "Avanti 20 in. 2.1 cu. ft. Electric Range in White",
        "Brand": "Avanti",
        "ImageUrl": "https://images.homedepot-static.com/productImages/0aeeef09-a59f-4980-b21c-a5b7d5a0455b/svn/white-avanti-single-oven-electric-ranges-er20p0wg-64_1000.jpg",
        "ProductPageUrl": "https://www.homedepot.com/p/Avanti-20-in-2-1-cu-ft-Electric-Range-in-White-ER20P0WG/301398974",
        "Description": "This Avanti 20 in. Electric Range Comes with a Backsplash and Storage Drawer. It features 4 coil burners, 2.1 cu. ft. capacity, deluxe see-thru glass oven door, oven cavity light, a backsplash and leveling legs. Fits great in small areas where most regular size stoves wont. Color: White.",
        "depth": "34.5",
        "height": "35",
        "width": "18.5",
        "ratingValue": "2.6667",
        "reviewCount": "3",
        "price": 753.78,
        "priceValidUntil": "7/4/2021"
    },
    "205390028": {
        "product_id": 205390028,
        "modelNbr": "ECK240BP",
        "Category": "APPLIANCES",
        "ApplType": "COOKING",
        "Type1": "FREE STANDING GAS",
        "Type2": "OTHER",
        "Title": "Premier 24 in. 2.97 cu. ft. Electric Range in Black",
        "Brand": "PREMIER",
        "ImageUrl": "https://images.homedepot-static.com/productImages/eee75db8-7208-4a32-a984-be325178802d/svn/black-premier-single-oven-electric-ranges-eck240bp-64_1000.jpg",
        "ProductPageUrl": "https://www.homedepot.com/p/Premier-24-in-2-97-cu-ft-Electric-Range-in-Black-ECK240BP/205390028",
        "Description": "Ideal for kitchenettes, small kitchens, studio apartments or any meal-prep area with space constraints, this 24 in. Freestanding Electric Range from Premier is a dependable cooking machine for any chef. It has one 8 in. burner and three 6 in. burners to handle an assortment of pots and pans, while a spacious 2.97 cu. ft. oven with two adjustable-height racks is at your disposal for baking at temperatures up to 500°F. A broil setting is also available to cook items under intense heat in close proximity to the upper heating element for browning and searing. Color: Black.",
        "depth": "43",
        "height": "15",
        "width": "19",
        "ratingValue": "4.1765",
        "reviewCount": "17",
        "price": 897.2,
        "priceValidUntil": "7/4/2021"
    },
    "313973586": {
        "product_id": 313973586,
        "modelNbr": "GL1FR24ASSARN",
        "Category": "APPLIANCES",
        "ApplType": "COOKING",
        "Type1": "FREE STANDING ELECTRIC",
        "Type2": "OTHER",
        "Title": "Galanz 24 in. Electric Range in Stainless Steel 2.2 cu. ft. Oven, Silver",
        "Brand": "Galanz",
        "ImageUrl": "https://images.homedepot-static.com/productImages/d72b5ca8-242b-4df0-b5bd-83962f6f6d6d/svn/stainless-steel-galanz-single-oven-electric-ranges-gl1fr24assarn-64_1000.jpg",
        "ProductPageUrl": "https://www.homedepot.com/p/Galanz-24-in-Electric-Range-in-Stainless-Steel-2-2-cu-ft-Oven-GL1FR24ASSARN/313973586",
        "Description": "The Galanz 24 in. wide, 2.2 cu. ft. radiant Range. This freestanding electric range with radiant cooktop is ideal for smaller spaces either in an apartment, cabin or just smaller kitchen. However, don't let the smaller width fool you it can still prepare family size meals. The 2200-Watt high output burner is ideal for searing at high heat but has the ability to change to a low simmer without moving the pot or pan. The European convection oven features several cooking modes to get outstanding results. It's 4 burner flush cooktop can accommodate different pan sizes. Galanz Appliances provide outstanding technology and great quality to bring you fantastic value in Kitchen appliances. With a modern sleek design, this suite of appliances is ideal for your family!. Color: Stainless Steel.",
        "depth": "41",
        "height": "17.9",
        "width": "13.1",
        "ratingValue": "5.0",
        "reviewCount": "3",
        "price": 999.99,
        "priceValidUntil": "07/10/2021"
    },
    "309372256": {
        "product_id": 309372256,
        "modelNbr": "PRE2417GB",
        "Category": "APPLIANCES",
        "ApplType": "COOKING",
        "Type1": "FREE STANDING ELECTRIC",
        "Type2": "OTHER",
        "Title": "PREMIUM 24 in. 2.7 cu. ft. Electric Range in Black with Stainless Steel Door",
        "Brand": "PREMIUM",
        "ImageUrl": "https://images.homedepot-static.com/productImages/7919aef2-ab12-43be-bc4c-cd9e1601a21b/svn/black-with-stainless-steel-door-premium-single-oven-electric-ranges-pre2417gb-64_1000.jpg",
        "ProductPageUrl": "https://www.homedepot.com/p/PREMIUM-24-in-2-7-cu-ft-Electric-Range-in-Black-with-Stainless-Steel-Door-PRE2417GB/309372256",
        "Description": "PREMIUM's 24 in. 2.7 cu. ft. Electric Range in Black with Stainless Steel Door is the perfect appliance for your apartment, condo or office kitchen. The stylish black color with stainless steel accents livens up any kitchen and matches any decor. Just as in larger units there is an in-door window and oven light to allow users to check on food while it is cooking, 2 adjustable wire racks, a broiler tray and grid included, and a handy removable storage drawer. With its small footprint, it conserves space while providing all the functionality you need to cook healthy meals at home.",
        "depth": "33.86",
        "height": "17.13",
        "width": "13.78",
        "ratingValue": "2.7778",
        "reviewCount": "9",
        "price": 679.82,
        "priceValidUntil": "7/4/2021"
    },
    "305572839": {
        "product_id": 305572839,
        "modelNbr": "WFE500M4HS",
        "Category": "APPLIANCES",
        "ApplType": "COOKING",
        "Type1": "FREE STANDING ELECTRIC",
        "Type2": "OTHER",
        "Title": "Whirlpool 2.96 cu. ft. Single Oven Electric Range with Upswept Spill Guard Cooktop in Stainless Steel, Silver",
        "Brand": "Whirlpool",
        "ImageUrl": "https://images.homedepot-static.com/productImages/3cbeb342-468a-4d50-99e5-15f7bcb05bf1/svn/stainless-steel-whirlpool-single-oven-electric-ranges-wfe500m4hs-64_1000.jpg",
        "ProductPageUrl": "https://www.homedepot.com/p/Whirlpool-2-96-cu-ft-Single-Oven-Electric-Range-with-Upswept-Spill-Guard-Cooktop-in-Stainless-Steel-WFE500M4HS/305572839",
        "Description": "Serve up something for everyone, even in tight kitchens, with a small electric range. This stove meets the Standards for Accessible Design specified by the Americans with Disabilities Act and features an indicator light that lets you know when the oven is hot, even after it's been turned off. When messes happen, the porcelain-coated steel cooktop easily wipes clean. Color: Stainless Steel.",
        "depth": "42.5",
        "height": "15",
        "width": "19",
        "ratingValue": "4.52",
        "reviewCount": "25",
        "price": 1169,
        "priceValidUntil": "07/14/2021"
    }
}